grid/__init__.py
grid/repl.py
grid/sdk/__init__.py
grid/sdk/resource_manager.py
grid/sdk/session_manager.py
grid/sdk/commander/client.py
grid/sdk/commander/core.py
grid/sdk/commander/server.py
grid/utils/airgen_utils.py
grid/utils/azcopy_downloader.py
grid/utils/config_handler.py
grid/utils/docker-compose.yml
grid/utils/grid_asset_downloader.py
grid/utils/isaac_utils.py
grid/utils/log_formatter.py
sf_grid-0.5.0.dist-info/METADATA
sf_grid-0.5.0.dist-info/WHEEL
sf_grid-0.5.0.dist-info/entry_points.txt
sf_grid-0.5.0.dist-info/RECORD
