Metadata-Version: 2.4
Name: sf-grid
Version: 0.5.0
Summary: General Robot Intelligence Development Platform - Enterprise Console
Project-URL: Homepage, https://scaledfoundations.ai
Author-email: Scaled Foundations <info@scaledfoundations.ai>
Classifier: Operating System :: OS Independent
Classifier: Programming Language :: Python :: 3
Requires-Python: >=3.11
Requires-Dist: art
Requires-Dist: docker
Requires-Dist: fastapi
Requires-Dist: httpx
Requires-Dist: packaging
Requires-Dist: paramiko
Requires-Dist: pyjwt
Requires-Dist: pyyaml
Requires-Dist: tabulate
Requires-Dist: uvicorn
